
<TimeML
    xmlns:xsi="http://www.w3.org/2001/XMLSchema-instance"
    xsi:noNamespaceSchemaLocation="../../dtd/timeml_1.2.1.xsd">

<DOCNO> WSJ891030-0087 </DOCNO>
<DD> = 891030 </DD>
<AN> 891030-0087. </AN>
<HL> New Securities Issues </HL>
<DD> 10/30/89 </DD>
<SO> WALL STREET JOURNAL (J) </SO>
<CO> SUNW T.CM EUROP F </CO>
<IN> BOND MARKET NEWS (BON) </IN>
<TEXT>
   The following were among Friday's offerings and pricings in the U.S. and non-U.S. capital markets, with terms and syndicate manager, as compiled by Dow Jones Capital Markets Report: 
@ CORPORATES 

   Sun Microsystems Inc. -- $125 million of 6 3/8% convertible subordinated debentures due Oct. 15, 1999, priced at 84.90 to yield 7.51%. 
The debentures are convertible into common stock at $25 a share, representing a 24% conversion premium over Thursday's closing price. 
Rated single-B-1 by Moody's Investors Service Inc. and single-B-plus by Standard amp Poor's Corp., the issue will be sold through underwriters led by Goldman, Sachs amp Co. 

   Hertz Corp. -- $100 million of senior notes due Nov. 1, 2009, priced at par to yield 9%. 
The issue, which is puttable back to the company in 1999, was priced at a spread of 110 basis points above the Treasury's 10-year note. 
Rated single-A-3 by Moody's and triple-B by SampP, the issue will be sold through underwriters led by Merrill Lynch Capital Markets. 
@ EUROBONDS 

   Canadian Imperial Bank of Commerce (Canada) -- 10 billion yen of 5.7% bonds due Nov. 17, 1992, priced at 101 1/4 to yield 5.75% less full fees, via LTCB International Ltd. Fees 1 3/8. 

</TEXT>




























































</TimeML>
